
{"items":[{"name":"Top","href":"index.html","topicHref":"index.html"},{"name":"Introduction","href":"intro/index.html","topicHref":"intro/index.html"},{"name":"Setup","href":"setup/index.html","topicHref":"setup/index.html"},{"name":"Rule","href":"rule/index.html","topicHref":"rule/index.html"},{"name":"About Local Enviroment","href":"local/index.html","topicHref":"local/index.html"},{"name":"About Evaluation Enviroment","href":"evaluation/index.html","topicHref":"evaluation/index.html"},{"name":"Other","href":"other/index.html","topicHref":"other/index.html"},{"name":"To Japanese Page","href":"../index.html","topicHref":"../index.html"}]}